mobilevids/__init__.py
mobilevids/define.py
mobilevids/dispatcher.py
mobilevids/downloader.py
mobilevids/imagetoascii.py
mobilevids/network.py
mobilevids/options.py
mobilevids_dl-1.0.6.dist-info/AUTHORS.md
mobilevids_dl-1.0.6.dist-info/LICENSE
mobilevids_dl-1.0.6.dist-info/METADATA
mobilevids_dl-1.0.6.dist-info/WHEEL
mobilevids_dl-1.0.6.dist-info/entry_points.txt
mobilevids_dl-1.0.6.dist-info/top_level.txt
mobilevids_dl-1.0.6.dist-info/RECORD
