Metadata-Version: 2.1
Name: mobilevids-dl
Version: 1.0.6
Summary: Script for downloading Movies and Shows from mobilevids.org
Home-page: https://github.com/ahron-maslin/mobilevids-dl
Maintainer: Aharon Maslin
Maintainer-email: aronmas613@gmail.com
License: LGPL
Keywords: mpbilevids-dl,mobilevids,download,entertainment,video
Platform: any
Classifier: Development Status :: 4 - Beta
Classifier: Environment :: Console
Classifier: Intended Audience :: End Users/Desktop
Classifier: License :: OSI Approved :: GNU Lesser General Public License v3 or later (LGPLv3+)
Classifier: Operating System :: OS Independent
Classifier: Programming Language :: Python :: 3.8
Classifier: Programming Language :: Python :: Implementation :: CPython
Classifier: Programming Language :: Python :: Implementation :: PyPy
Classifier: Programming Language :: Python
Classifier: Topic :: Education
License-File: LICENSE
License-File: AUTHORS.md
Requires-Dist: ascii-magic ==2.3.0
Requires-Dist: backports.shutil-get-terminal-size ==1.0.0
Requires-Dist: certifi ==2023.7.22
Requires-Dist: charset-normalizer ==3.1.0
Requires-Dist: colorama ==0.4.6
Requires-Dist: idna ==3.4
Requires-Dist: Pillow ==10.0.1
Requires-Dist: pypdl ==0.0.6
Requires-Dist: reprint ==0.6.0
Requires-Dist: requests ==2.31.0
Requires-Dist: six ==1.16.0
Requires-Dist: urllib3 ==1.26.17
Requires-Dist: wget ==3.2
Provides-Extra: dev
